odoo/addons/odoo_repository_migration/README.rst
odoo/addons/odoo_repository_migration/__init__.py
odoo/addons/odoo_repository_migration/__manifest__.py
odoo/addons/odoo_repository_migration/hooks.py
odoo/addons/odoo_repository_migration/data/queue_job.xml
odoo/addons/odoo_repository_migration/migrations/16.0.1.0.1/post-migration.py
odoo/addons/odoo_repository_migration/migrations/16.0.1.1.0/post-migration.py
odoo/addons/odoo_repository_migration/migrations/16.0.1.2.0/post-migration.py
odoo/addons/odoo_repository_migration/migrations/16.0.1.3.0/post-migration.py
odoo/addons/odoo_repository_migration/models/__init__.py
odoo/addons/odoo_repository_migration/models/odoo_migration_path.py
odoo/addons/odoo_repository_migration/models/odoo_module_branch.py
odoo/addons/odoo_repository_migration/models/odoo_module_branch_migration.py
odoo/addons/odoo_repository_migration/models/odoo_module_branch_timeline.py
odoo/addons/odoo_repository_migration/models/odoo_repository.py
odoo/addons/odoo_repository_migration/readme/CONTRIBUTORS.md
odoo/addons/odoo_repository_migration/readme/DESCRIPTION.md
odoo/addons/odoo_repository_migration/readme/USAGE.md
odoo/addons/odoo_repository_migration/security/ir.model.access.csv
odoo/addons/odoo_repository_migration/static/description/icon.png
odoo/addons/odoo_repository_migration/static/description/index.html
odoo/addons/odoo_repository_migration/tests/__init__.py
odoo/addons/odoo_repository_migration/tests/test_odoo_module_branch.py
odoo/addons/odoo_repository_migration/utils/__init__.py
odoo/addons/odoo_repository_migration/utils/scanner.py
odoo/addons/odoo_repository_migration/views/odoo_migration_path.xml
odoo/addons/odoo_repository_migration/views/odoo_module_branch.xml
odoo/addons/odoo_repository_migration/views/odoo_module_branch_migration.xml
odoo/addons/odoo_repository_migration/views/odoo_module_branch_timeline.xml
odoo/addons/odoo_repository_migration/views/odoo_repository.xml
odoo_addon_odoo_repository_migration-16.0.1.3.2.dist-info/METADATA
odoo_addon_odoo_repository_migration-16.0.1.3.2.dist-info/WHEEL
odoo_addon_odoo_repository_migration-16.0.1.3.2.dist-info/top_level.txt
odoo_addon_odoo_repository_migration-16.0.1.3.2.dist-info/RECORD
