Metadata-Version: 2.1
Name: odoo-addon-odoo_repository_migration
Version: 16.0.1.3.2
Summary: Collect modules migration data for Odoo Repositories.
Home-page: https://github.com/OCA/module-composition-analysis
Author: Camptocamp, Odoo Community Association (OCA)
Author-email: support@odoo-community.org
License: AGPL-3
Classifier: Programming Language :: Python
Classifier: Framework :: Odoo
Classifier: Framework :: Odoo :: 16.0
Classifier: License :: OSI Approved :: GNU Affero General Public License v3
Requires-Python: >=3.10
Requires-Dist: oca-port
Requires-Dist: odoo-addon-odoo-repository<16.1dev,>=16.0dev
Requires-Dist: odoo<16.1dev,>=16.0a
